backup_sendgrid_templates/__init__.py
backup_sendgrid_templates/__main__.py
backup_sendgrid_templates/aws_utils.py
backup_sendgrid_templates/service.py
backup_sendgrid_templates/strategies.py
backup_sendgrid_templates-0.9.0.dist-info/LICENSE
backup_sendgrid_templates-0.9.0.dist-info/METADATA
backup_sendgrid_templates-0.9.0.dist-info/WHEEL
backup_sendgrid_templates-0.9.0.dist-info/entry_points.txt
backup_sendgrid_templates-0.9.0.dist-info/top_level.txt
backup_sendgrid_templates-0.9.0.dist-info/RECORD
