Metadata-Version: 2.1
Name: backup-sendgrid-templates
Version: 0.9.0
Summary: Backup all your Sendgrid templates on file system or on a S3 bucket.
Author: Sergio Morstabilini
License: MIT License        
Project-URL: Homepage, https://github.com/backupSendgridTemplates/backupSendgridTemplates
Keywords: sendgrid,backup
Classifier: License :: OSI Approved :: MIT License
Classifier: Programming Language :: Python
Classifier: Programming Language :: Python :: 3
Requires-Python: >=3.8
License-File: LICENSE
Requires-Dist: sendgrid (>=6.9.7)
Requires-Dist: boto3 (>=1.14.56)
